celeri/__init__.py
celeri/celeri.py
celeri/celeri_closure.py
celeri/celeri_util.py
celeri/cli.py
celeri/config.py
celeri/constants.py
celeri/mesh.py
celeri/model.py
celeri/operators.py
celeri/optimize.py
celeri/optimize_sqp.py
celeri/output.py
celeri/plot.py
celeri/solve.py
celeri/solve_mcmc.py
celeri/spatial.py
celeri/okada/auto-triangulation.md
celeri/okada/cutde_okada.py
celeri/okada/figures/triangulation_schematic.py
celeri/okada/figures/triangulation_schematic.svg
celeri/scripts/celeri_forward.py
celeri/scripts/celeri_solve.py
celeri/scripts/create_bel_mesh.py
celeri/scripts/create_grid_station.py
celeri/scripts/msh2stl.py
celeri/scripts/segmesh.py
celeri/scripts/snap_segments.py
celeri/scripts/stl2msh.py
celeri-0.0.4.dist-info/METADATA
celeri-0.0.4.dist-info/WHEEL
celeri-0.0.4.dist-info/entry_points.txt
celeri-0.0.4.dist-info/licenses/LICENSE
celeri-0.0.4.dist-info/RECORD
