Metadata-Version: 2.4
Name: celeri
Version: 0.0.4
Summary: Next generation earthquake cycle kinematics
Project-URL: Homepage, https://github.com/brendanjmeade/celeri
Author-email: Brendan Meade <brendanjmeade@gmail.com>
License: MIT License
License-File: LICENSE
Classifier: Intended Audience :: Science/Research
Classifier: License :: OSI Approved :: MIT License
Classifier: Operating System :: OS Independent
Classifier: Programming Language :: Python :: 3
Classifier: Topic :: Scientific/Engineering
Classifier: Topic :: Scientific/Engineering :: Physics
Classifier: Topic :: Scientific/Engineering :: Visualization
Requires-Python: >=3.11
Requires-Dist: addict
Requires-Dist: cartopy
Requires-Dist: colorcet
Requires-Dist: cutde>=25.7.24
Requires-Dist: cvxopt
Requires-Dist: cvxpy
Requires-Dist: gmsh
Requires-Dist: h5py
Requires-Dist: ipykernel
Requires-Dist: ipython
Requires-Dist: loguru
Requires-Dist: matplotlib
Requires-Dist: meshio
Requires-Dist: numba
Requires-Dist: numpy
Requires-Dist: nutpie
Requires-Dist: pandas
Requires-Dist: papermill
Requires-Dist: pyarrow
Requires-Dist: pydantic
Requires-Dist: pymc
Requires-Dist: pyproj
Requires-Dist: pytest
Requires-Dist: scipy
Requires-Dist: shapely
Requires-Dist: spherical-geometry
Requires-Dist: tqdm
Requires-Dist: xarray
Requires-Dist: zarr
